kragle/__init__.py
kragle/debouncer.py
kragle-0.1.1.dist-info/WHEEL
kragle-0.1.1.dist-info/METADATA
kragle-0.1.1.dist-info/RECORD
