Metadata-Version: 2.1
Name: kragle
Version: 0.1.1
Summary: glue and tape
Home-page: https://github.com/arni-inaba/kragle
License: MIT
Author: Arni Inaba Kjartansson
Author-email: arni@inaba.is
Requires-Python: >=3.7,<4.0
Classifier: License :: OSI Approved :: MIT License
Classifier: Programming Language :: Python :: 3
Classifier: Programming Language :: Python :: 3.7
Project-URL: Repository, https://github.com/arni-inaba/kragle
